mobipy/__init__.py
mobipy/dataset_selector.py
mobipy/exceptions.py
mobipy/identifier.py
mobipy/metrics.py
mobipy/selector.py
mobipy/utils.py
mobipy-1.0.0.dist-info/LICENSE
mobipy-1.0.0.dist-info/METADATA
mobipy-1.0.0.dist-info/WHEEL
mobipy-1.0.0.dist-info/top_level.txt
mobipy-1.0.0.dist-info/RECORD
