Metadata-Version: 2.1
Name: mobipy
Version: 1.0.0
Summary: A library for analyzing user mobility patterns
Home-page: http://github.com/pedrohcm/mobipy
Author: Pedro Maia
Author-email: pedro.maia@ccc.ufcg.edu.br
License: UNKNOWN
Platform: UNKNOWN
Classifier: Programming Language :: Python :: 3.6
Classifier: License :: OSI Approved :: MIT License
Classifier: Operating System :: OS Independent
Requires-Python: >=3.6
Requires-Dist: geopy
Requires-Dist: pandas
Requires-Dist: numpy
Requires-Dist: sklearn
Requires-Dist: shapely
